plugin.py
pytest_slow-0.0.3.dist-info/LICENSE
pytest_slow-0.0.3.dist-info/WHEEL
pytest_slow-0.0.3.dist-info/METADATA
pytest_slow-0.0.3.dist-info/RECORD
